nbmelt.py
nbmelt-1.2.0.data/data/etc/jupyter/jupyter_notebook_config.d/nbmelt.json
nbmelt-1.2.0.data/data/etc/jupyter/jupyter_server_config.d/nbmelt.json
nbmelt-1.2.0.dist-info/LICENSE
nbmelt-1.2.0.dist-info/METADATA
nbmelt-1.2.0.dist-info/WHEEL
nbmelt-1.2.0.dist-info/top_level.txt
nbmelt-1.2.0.dist-info/RECORD
