Metadata-Version: 2.1
Name: nbmelt
Version: 1.2.0
Summary: Shutdown notebooks that don't get used
Home-page: http://github.com/minrk/nbmelt
Author: Min Ragan-Kelley
Author-email: benjaminrk@gmail.com
License: BSD
Platform: UNKNOWN
Classifier: License :: OSI Approved :: BSD License
Classifier: Programming Language :: Python :: 2
Classifier: Programming Language :: Python :: 3
